{
  "project_info": {
    "project_number": "343504989538",
    "project_id": "collegefitit",
    "storage_bucket": "collegefitit.appspot.com"
  },
  "client": [
    {
      "client_info": {
        "mobilesdk_app_id": "1:343504989538:android:cca6a85fcf249863c5103b",
        "android_client_info": {
          "package_name": "com.example.collegefixit"
        }
      },
      "oauth_client": [],
      "api_key": [
        {
          "current_key": "AIzaSyByG9MNwqiMonSPmsUihGX5DDF8KIFI5cA"
        }
      ],
      "services": {
        "appinvite_service": {
          "other_platform_oauth_client": []
        }
      }
    }
  ],
  "configuration_version": "1"
}